zmq/__init__.pxd
zmq/__init__.py
zmq/__init__.pyi
zmq/_future.py
zmq/_typing.py
zmq/asyncio.py
zmq/constants.py
zmq/decorators.py
zmq/error.py
zmq/py.typed
zmq/auth/__init__.py
zmq/auth/asyncio.py
zmq/auth/base.py
zmq/auth/certs.py
zmq/auth/ioloop.py
zmq/auth/thread.py
zmq/backend/__init__.py
zmq/backend/__init__.pyi
zmq/backend/select.py
zmq/backend/cffi/__init__.py
zmq/backend/cffi/_cdefs.h
zmq/backend/cffi/_poll.py
zmq/backend/cffi/context.py
zmq/backend/cffi/devices.py
zmq/backend/cffi/error.py
zmq/backend/cffi/message.py
zmq/backend/cffi/socket.py
zmq/backend/cffi/utils.py
zmq/backend/cython/__init__.pxd
zmq/backend/cython/__init__.py
zmq/backend/cython/_device.cpython-312.so
zmq/backend/cython/_poll.cpython-312.so
zmq/backend/cython/_proxy_steerable.cpython-312.so
zmq/backend/cython/_version.cpython-312.so
zmq/backend/cython/checkrc.pxd
zmq/backend/cython/constant_enums.pxi
zmq/backend/cython/context.cpython-312.so
zmq/backend/cython/context.pxd
zmq/backend/cython/error.cpython-312.so
zmq/backend/cython/libzmq.pxd
zmq/backend/cython/message.cpython-312.so
zmq/backend/cython/message.pxd
zmq/backend/cython/socket.cpython-312.so
zmq/backend/cython/socket.pxd
zmq/backend/cython/utils.cpython-312.so
zmq/devices/__init__.py
zmq/devices/basedevice.py
zmq/devices/monitoredqueue.cpython-312.so
zmq/devices/monitoredqueue.pxd
zmq/devices/monitoredqueue.py
zmq/devices/monitoredqueuedevice.py
zmq/devices/proxydevice.py
zmq/devices/proxysteerabledevice.py
zmq/eventloop/__init__.py
zmq/eventloop/_deprecated.py
zmq/eventloop/future.py
zmq/eventloop/ioloop.py
zmq/eventloop/zmqstream.py
zmq/green/__init__.py
zmq/green/core.py
zmq/green/device.py
zmq/green/poll.py
zmq/green/eventloop/__init__.py
zmq/green/eventloop/ioloop.py
zmq/green/eventloop/zmqstream.py
zmq/log/__init__.py
zmq/log/__main__.py
zmq/log/handlers.py
zmq/ssh/__init__.py
zmq/ssh/forward.py
zmq/ssh/tunnel.py
zmq/sugar/__init__.py
zmq/sugar/__init__.pyi
zmq/sugar/attrsettr.py
zmq/sugar/context.py
zmq/sugar/frame.py
pyzmq_qpython-25.1.2.dist-info/METADATA
pyzmq_qpython-25.1.2.dist-info/WHEEL
pyzmq_qpython-25.1.2.dist-info/top_level.txt
pyzmq_qpython-25.1.2.dist-info/RECORD
